CHANGELOG.rst
LICENSE
MANIFEST.in
README.rst
requirements.txt
setup.py
docs/Makefile
docs/api.rst
docs/conf.py
docs/guide.rst
docs/index.rst
docs/license.rst
docs/requirements-rtd.txt
docs/_build/html/_images/18569_chem_shifts_GLU_CA_CB_THR_HA_HB.png
docs/_build/html/_images/18569_chem_shifts_GLU_THR_CA_CB_CG_CG2.png
docs/_build/html/_images/18569_chem_shifts_all.png
docs/_build/html/_sources/api.rst.txt
docs/_build/html/_sources/guide.rst.txt
docs/_build/html/_sources/index.rst.txt
docs/_build/html/_sources/license.rst.txt
docs/_build/html/_sources/ttrl.ipynb.txt
docs/_build/html/_sources/tutorial.rst.txt
docs/_build/html/_static/comment-bright.png
docs/_build/html/_static/comment-close.png
docs/_build/html/_static/comment.png
docs/_build/html/_static/down-pressed.png
docs/_build/html/_static/down.png
docs/_build/html/_static/file.png
docs/_build/html/_static/minus.png
docs/_build/html/_static/plus.png
docs/_build/html/_static/up-pressed.png
docs/_build/html/_static/up.png
docs/_build/html/_static/fonts/fontawesome-webfont.svg
docs/_build/html/_static/images/18569_chem_shifts_GLU_CA_CB_THR_HA_HB.png
docs/_build/html/_static/images/18569_chem_shifts_GLU_THR_CA_CB_CG_CG2.png
docs/_build/html/_static/images/18569_chem_shifts_all.png
docs/_build/html/_static/images/nmrstarlib_logo.png
docs/_build/html/_static/nmrstarfiles/out/18569_HNcoCACB.txt
docs/_build/html/_static/nmrstarfiles/out/18569_HNcoCACB_ssv_HCN.txt
docs/_build/html/_static/nmrstarfiles/out/18569_HNcoCACB_ssv_HCN_chi2.txt
docs/_build/html/_static/nmrstarfiles/out/18569_HNcoCACB_ssv_HN.txt
docs/_build/html/_static/nmrstarfiles/out/18569_HNcoCACB_ssv_HN_chi2.txt
docs/_build/html/_static/nmrstarfiles/out/18569_HNcoCACB_tsv_HN.txt
docs/_build/html/_static/nmrstarfiles/out/18569_NCACX_custom.txt
docs/_build/html/_static/nmrstarfiles/out/18569_chem_shifts_GLU_CA_CB_THR_HA_HB_0.png
docs/_build/html/_static/nmrstarfiles/out/18569_chem_shifts_GLU_THR_CA_CB_CG_CG2_0.png
nmrstarlib.egg-info/PKG-INFO
nmrstarlib.egg-info/SOURCES.txt
nmrstarlib.egg-info/dependency_links.txt
nmrstarlib.egg-info/requires.txt
nmrstarlib.egg-info/top_level.txt
