Metadata-Version: 1.1
Name: nmrstarlib
Version: 2.1.1
Summary: Python library for parsing data from NMR-STAR format files
Home-page: https://github.com/MoseleyBioinformaticsLab/nmrstarlib
Author: Andrey Smelter
Author-email: andrey.smelter@gmail.com
License: MIT
Keywords: BMRB NMR-STAR parsing nmrstarlib
Platform: any
Classifier: Development Status :: 4 - Beta
Classifier: Environment :: Console
Classifier: Intended Audience :: Developers
Classifier: Intended Audience :: Science/Research
Classifier: License :: OSI Approved :: MIT License
Classifier: Operating System :: OS Independent
Classifier: Programming Language :: Python :: 2.7
Classifier: Programming Language :: Python :: 3.4
Classifier: Programming Language :: Python :: 3.5
Classifier: Programming Language :: Python :: 3.6
Classifier: Topic :: Scientific/Engineering :: Bio-Informatics
Classifier: Topic :: Software Development :: Libraries :: Python Modules
